Workbook
Name aporte: Planilha1!$D$18
Name patrimonio: Planilha1!$D$21
Name qtd_anos: Planilha1!$D$19
Name rendimento_carteira: Planilha1!$D$14
Name salario: Planilha1!$D$13
Name sugestao_investimento: Planilha1!$D$15
Name taxa_mensal: Planilha1!$D$20

Sheet Planilha1
B12: CONFIGURAÇÕES
B13: Salário | D13: 4200
B14: Rendimento Carteira | D14: 0.006
B15: Sugestão de Investimento (30%) | D15: =D13*30% -> 1260
B17: INVESTIMENTO MENSAL
B18: Quanto investir por mês? | D18: 2000
B19: Por quantos anos? | D19: 10
B20: Taxa de rendimento mensal? | D20: 0.01079
B21: Quanto de Patrimônio acumulado? | D21: =FV(taxa_mensal,qtd_anos*12,aporte*-1) -> 486568.43
B22: Dividendos mensais? | D22: =patrimonio*rendimento_carteira -> 2919.4106
A24: 2 | B24: CENÁRIOS | D24: Dividendo
A25: 2 | B25: Quanto em 2 anos? | C25: =FV($D$20,$A25*12,$D$18*-1) -> 54455.255 | D25: =C25*rendimento_carteira -> 326.73153
A26: 5 | B26: Quanto em 5 anos? | C26: =FV($D$20,$A26*12,$D$18*-1) -> 167553.83 | D26: =C26*rendimento_carteira -> 1005.323
A27: 10 | B27: Quanto em 10 anos? | C27: =FV($D$20,$A27*12,$D$18*-1) -> 486568.43 | D27: =C27*rendimento_carteira -> 2919.4106
A28: 20 | B28: Quanto em 20 anos? | C28: =FV($D$20,$A28*12,$D$18*-1) -> 2250396.8 | D28: =C28*rendimento_carteira -> 13502.381
A29: 30 | B29: Quanto em 30 anos? | C29: =FV($D$20,$A29*12,$D$18*-1) -> 8644339.3 | D29: =C29*rendimento_carteira -> 51866.036
B32: PERFIL | C32: Moderado
B33: VALOR A SER INVESTIDO POR MÊS | C33: =aporte -> 2000
B35: TIPO DE FII | C35: Percentual Sugerido | D35: Valores
B36: PAPEL | C36: =VLOOKUP($C$32&"-"&B36,Planilha2!A:D,4,) -> 0.32 | D36: =C36*$C$33 -> 640
B37: TIJOLO | C37: =VLOOKUP($C$32&"-"&B37,Planilha2!A:D,4,) -> 0.35 | D37: =C37*$C$33 -> 700
B38: HÍBRIDOS | C38: =VLOOKUP($C$32&"-"&B38,Planilha2!A:D,4,) -> 0.08 | D38: =C38*$C$33 -> 160
B39: FOFs | C39: =VLOOKUP($C$32&"-"&B39,Planilha2!A:D,4,) -> 0.05 | D39: =C39*$C$33 -> 100
B40: DESENVOLVIMENTO | C40: =VLOOKUP($C$32&"-"&B40,Planilha2!A:D,4,) -> 0.1 | D40: =C40*$C$33 -> 200
B41: HOTELARIAS | C41: =VLOOKUP($C$32&"-"&B41,Planilha2!A:D,4,) -> 0.1 | D41: =C41*$C$33 -> 200
D42: =SUM(D36:D41) -> 2000

Sheet Planilha2
A2: CHAVE | B2: PERFIL | C2: TIPO DE FII | D2: %
A3: =B3&"-"&C3 -> Conservador-PAPEL | B3: Conservador | C3: PAPEL | D3: 0.3 | G3: %
A4: =B4&"-"&C4 -> Conservador-TIJOLO | B4: Conservador | C4: TIJOLO | D4: 0.5 | F4: Moderado-TIJOLO | G4: =VLOOKUP(F4,$A:$D,4,FALSE) -> 0.35
A5: =B5&"-"&C5 -> Conservador-HÍBRIDOS | B5: Conservador | C5: HÍBRIDOS | D5: 0.1
A6: =B6&"-"&C6 -> Conservador-FOFs | B6: Conservador | C6: FOFs | D6: 0.1
A7: =B7&"-"&C7 -> Conservador-DESENVOLVIMENTO | B7: Conservador | C7: DESENVOLVIMENTO | D7: 0
A8: =B8&"-"&C8 -> Conservador-HOTELARIAS | B8: Conservador | C8: HOTELARIAS | D8: 0
A9: =B9&"-"&C9 -> Moderado-PAPEL | B9: Moderado | C9: PAPEL | D9: 0.32
A10: =B10&"-"&C10 -> Moderado-TIJOLO | B10: Moderado | C10: TIJOLO | D10: 0.35
A11: =B11&"-"&C11 -> Moderado-HÍBRIDOS | B11: Moderado | C11: HÍBRIDOS | D11: 0.08
A12: =B12&"-"&C12 -> Moderado-FOFs | B12: Moderado | C12: FOFs | D12: 0.05
A13: =B13&"-"&C13 -> Moderado-DESENVOLVIMENTO | B13: Moderado | C13: DESENVOLVIMENTO | D13: 0.1
A14: =B14&"-"&C14 -> Moderado-HOTELARIAS | B14: Moderado | C14: HOTELARIAS | D14: 0.1
A15: =B15&"-"&C15 -> Agressivo-PAPEL | B15: Agressivo | C15: PAPEL | D15: 0.5
A16: =B16&"-"&C16 -> Agressivo-TIJOLO | B16: Agressivo | C16: TIJOLO | D16: 0.1
... A20: =B20&"-"&C20 -> Agressivo-HOTELARIAS | B20: Agressivo | C20: HOTELARIAS | D20: 0.1
